[
  {"name": "Karmine Corp", "players": ["Vatira", "Atow.", "juicy"], "rating": 2029, "color": "blue", "logo": "logos/KC.png"},
  {"name": "Team Vitality", "players": ["zen", "stizzy", "ExoTiiK"], "rating": 2011, "color": "blue", "logo": "logos/VIT.png"},
  {"name": "Gentle Mates", "players": ["Oski", "nass", "Archie"], "rating": 1996, "color": "blue", "logo": "logos/M8.png"},
  {"name": "Man City Esports", "players": ["Seikoo", "accro", "ejby"], "rating": 1889, "color": "blue", "logo": "logos/MC.png"},
  {"name": "Ninjas in Pyjamas", "players": ["Joreuz", "oaly.", "crr"], "rating": 1884, "color": "blue", "logo": "logos/NIP.png"},
  {"name": "Geekay Esports", "players": ["TempoH", "Joyo", "ApparentlyJack"], "rating": 1784, "color": "blue", "logo": "logos/GK.png"},
  {"name": "Kaydop Corp", "players": ["Alpha54", "Radosin", "mtzr"], "rating": 1867, "color": "blue", "logo": "logos/DEFAULT.png"},
  {"name": "Griddy Goose", "players": ["Rezears", "Tox", "bibbaba"], "rating": 1790, "color": "blue", "logo": "logos/GRG.png"},
  {"name": "NOVO Esports", "players": ["Nico", "GiuK", "rehzzy"], "rating": 1855, "color": "blue", "logo": "logos/NOVO.png"},
  {"name": "Magnifico", "players": ["AtomiK", "yujin", "AcroniK."], "rating": 1774, "color": "blue", "logo": "logos/MAG.png"},

  {"name": "NRG", "players": ["Daniel", "Atomic", "BeastMode"], "rating": 1925, "color": "red", "logo": "logos/NRG.png"},
  {"name": "Spacestation Gaming", "players": ["reveal", "diaz", "zach"], "rating": 1928, "color": "red", "logo": "logos/SSG.png"},
  {"name": "Shopify Rebellion", "players": ["Firstkiller", "kofyr", "Lj"], "rating": 1958, "color": "red", "logo": "logos/SR.png"},
  {"name": "Virtus.pro", "players": ["Tawk", "Wahvey", "2Piece"], "rating": 1865, "color": "red", "logo": "logos/VP.png"},
  {"name": "FUT Esports", "players": ["Chronic", "jstn.", "CHEESE."], "rating": 1882, "color": "red", "logo": "logos/FUT.png"},
  {"name": "Gen.G Mobil1 Racing", "players": ["MaJicBear", "frosty", "rise."], "rating": 1721, "color": "red", "logo": "logos/GENG.png"},
  {"name": "Dignitas", "players": ["Evoh", "bora", "Fiv3Up"], "rating": 1744.5, "color": "red", "logo": "logos/DIG.png"},

  {"name": "Twisted Minds", "players": ["trk511", "Nwpo", "M0nkey M00n"], "rating": 1985, "color": "green", "logo": "logos/TWIS.png"},
  {"name": "Team Falcons", "players": ["Rw9", "Kiileerrz", "dralii"], "rating": 1937, "color": "green", "logo": "logos/FLCN.png"},
  {"name": "R8 Esports", "players": ["Abdullah", "M7md", "Ghaazi"], "rating": 1877, "color": "green", "logo": "logos/R8.png"},
  {"name": "Stallions", "players": ["Nush", "Trook", "Twiz"], "rating": 1776, "color": "green", "logo": "logos/Stallions.png"},
  {"name": "DOS", "players": ["DrKnown", "ops", "Suspect"], "rating": 1731, "color": "green", "logo": "logos/DEFAULT.png"},
  
  {"name": "FURIA", "players": ["yANXNZ", "swiftt.", "Lostt."], "rating": 1907, "color": "yellow", "logo": "logos/FUR.png"},
  {"name": "MIBR", "players": ["Reysbull", "Sad", "Aztrø"], "rating": 1877, "color": "yellow", "logo": "logos/MIBR.png"},
  {"name": "BANANA", "players": ["Motta", "suco", "DRUFINHO"], "rating": 1685, "color": "yellow", "logo": "logos/DEFAULT.png"},
  {"name": "BS+COMPETITION", "players": ["kv1", "crn", "wisty"], "rating": 1784, "color": "yellow", "logo": "logos/BSC.png"},

  {"name": "Wildcard", "players": ["bananahead", "Fever", "Torsos"], "rating": 1789, "color": "magenta", "logo": "logos/WC.png"},
  {"name": "PWR", "players": ["gus", "Superlachie", "Fibérr"], "rating": 1746, "color": "magenta", "logo": "logos/PWR.png"}
]
